password_converter/__init__.py
password_converter/converter.py
password_converter/exceptions.py
password_converter/utils.py
password_converter-0.3.0.dist-info/LICENSE
password_converter-0.3.0.dist-info/METADATA
password_converter-0.3.0.dist-info/WHEEL
password_converter-0.3.0.dist-info/entry_points.txt
password_converter-0.3.0.dist-info/top_level.txt
password_converter-0.3.0.dist-info/RECORD
