Metadata-Version: 2.1
Name: password_converter
Version: 0.3.0
Summary: Convert Kaspersky password manager exports to Apple Password format
Author-email: Daniel Lozano Gómez <daniellg7@gmail.com>
License: MIT License
Project-URL: Homepage, https://github.com/Mr-Physicist/kaspersky_to_apple_parser
Project-URL: Documentation, https://github.com/Mr-Physicist/kaspersky_to_apple_parser#readme
Project-URL: Repository, https://github.com/Mr-Physicist/kaspersky_to_apple_parser.git
Project-URL: Issues, https://github.com/Mr-Physicist/kaspersky_to_apple_parser/issues
Keywords: password,converter,apple,security,kaspersky
Classifier: Development Status :: 4 - Beta
Classifier: Intended Audience :: End Users/Desktop
Classifier: License :: OSI Approved :: MIT License
Classifier: Programming Language :: Python :: 3.11
Classifier: Programming Language :: Python :: 3.12
Classifier: Programming Language :: Python :: 3.13
Requires-Python: >=3.11
License-File: LICENSE
Requires-Dist: typing-extensions>=4.0.0
Provides-Extra: dev
Requires-Dist: pytest>=7.0; extra == "dev"
Requires-Dist: pytest-cov>=4.0; extra == "dev"
Requires-Dist: black>=22.0; extra == "dev"
Requires-Dist: isort>=5.0; extra == "dev"
Requires-Dist: mypy>=1.0; extra == "dev"
Requires-Dist: flake8>=5.0; extra == "dev"
